django_mathcalc-0.1.dist-info/DESCRIPTION.rst
django_mathcalc-0.1.dist-info/METADATA
django_mathcalc-0.1.dist-info/RECORD
django_mathcalc-0.1.dist-info/WHEEL
django_mathcalc-0.1.dist-info/metadata.json
django_mathcalc-0.1.dist-info/top_level.txt
mathcalc/__init__.py
mathcalc/admin.py
mathcalc/apps.py
mathcalc/calcs.py
mathcalc/forms.py
mathcalc/models.py
mathcalc/tests.py
mathcalc/urls.py
mathcalc/views.py
mathcalc/migrations/__init__.py
mathcalc/templates/mathcalc/area_circle.html
mathcalc/templates/mathcalc/circle_result.html
mathcalc/templates/mathcalc/index.html
mathcalc/templates/mathcalc/perimeter_rectangle.html
mathcalc/templates/mathcalc/rectangle_result.html
